froeling/__init__.py
froeling/client.py
froeling/endpoints.py
froeling/exceptions.py
froeling/session.py
froeling/datamodels/__init__.py
froeling/datamodels/component.py
froeling/datamodels/facility.py
froeling/datamodels/generics.py
froeling/datamodels/notifications.py
froeling/datamodels/userdata.py
froeling_connect-2024.1.3.dist-info/LICENSE.txt
froeling_connect-2024.1.3.dist-info/METADATA
froeling_connect-2024.1.3.dist-info/WHEEL
froeling_connect-2024.1.3.dist-info/top_level.txt
froeling_connect-2024.1.3.dist-info/RECORD
