Metadata-Version: 2.2
Name: froeling-connect
Version: 2024.1.3
Summary: A python wrapper for the Fröling-Connect API
Home-page: https://github.com/Layf21/froeling-connect
Author: Layf
License:                                  Apache License
Keywords: froeling,fröling,fröling-connect,fröling connect
Requires-Python: >=3.9
License-File: LICENSE.txt
Requires-Dist: aiohttp
